{"id":"842435","slug":"842435","pathname":"/tienda/producto/842435","canonical":"https://www.haitech.pe/tienda/producto/842435","title":"Toner Cartucho Original RICOH IM-C3000 IM-C3500 I… | Haitech","description":"Toner Cartucho Original RICOH IM-C3000 IM-C3500 Amarillo — IM C3000/ IM C3500 (Rend 19,000) Desde S/ 688. Cotiza online con envío a todo el Perú.","image":"https://www.haitech.pe/categories/promonuevas-1.png","imageAlt":"Toner Cartucho Original RICOH IM-C3000 IM-C3500 IM C3000/ IM C3500 Amarillo (19,000 páginas al 5%)","ogType":"product","ogProduct":{"priceAmount":"185.90","priceCurrency":"USD","priceAmountPen":"688","availability":"out of stock","brand":"RICOH","retailerItemId":"842435"},"breadcrumbs":[{"label":"Inicio","href":"/"},{"label":"Productos","href":"/tienda"},{"label":"Suministros, Toner Originales","href":"/categoria/toner-suministros"},{"label":"Toner Cartucho Original RICOH IM-C3000 IM-C3500 IM C3000/ IM C3500 Amarillo (19,000 páginas al 5%)"}],"jsonLd":[{"@context":"https://schema.org","@type":"Product","name":"Toner Cartucho Original RICOH IM-C3000 IM-C3500 IM C3000/ IM C3500 Amarillo (19,000 páginas al 5%)","description":"Toner Cartucho Original RICOH IM-C3000 IM-C3500 Amarillo — IM C3000/ IM C3500 (Rend 19,000)","sku":"842435","brand":{"@type":"Brand","name":"RICOH"},"offers":{"@type":"Offer","url":"https://www.haitech.pe/tienda/producto/842435","availability":"https://schema.org/OutOfStock","seller":{"@type":"Organization","name":"Haitech"},"itemCondition":"https://schema.org/NewCondition","priceValidUntil":"2026-09-24","priceCurrency":"USD","price":"185.90"},"mpn":"IM C3000/ IM C3500","model":"IM C3000/ IM C3500"},{"@context":"https://schema.org","@type":"BreadcrumbList","itemListElement":[{"@type":"ListItem","position":1,"name":"Inicio","item":"https://www.haitech.pe/"},{"@type":"ListItem","position":2,"name":"Productos","item":"https://www.haitech.pe/tienda"},{"@type":"ListItem","position":3,"name":"Suministros, Toner Originales","item":"https://www.haitech.pe/categoria/toner-suministros"},{"@type":"ListItem","position":4,"name":"Toner Cartucho Original RICOH IM-C3000 IM-C3500 IM C3000/ IM C3500 Amarillo (19,000 páginas al 5%)"}]}],"robots":"index,follow"}
