{"id":"repuesto-m0edl427","slug":"repuesto-m0edl427","pathname":"/tienda/repuesto-m0edl427","canonical":"https://www.haitech.pe/tienda/repuesto-m0edl427","title":"SLIDER SHEET:ASS'Y Original PRO C9500… | HaiStore","description":"SLIDER SHEET:ASS'Y Original PRO C9500 (1,200,000 págs al 5%) Desde S/ 1,221. Cotiza online con envío a todo el Perú.","image":"https://www.haitech.pe/categories/promonuevas-1.png","imageAlt":"SLIDER SHEET:ASS'Y Original PRO C9500 (1,200,000 págs al 5%)","ogType":"product","ogProduct":{"priceAmount":"329.90","priceCurrency":"USD","priceAmountPen":"1221","availability":"out of stock","brand":"RICOH","retailerItemId":"M0EDL427"},"breadcrumbs":[{"label":"Inicio","href":"/"},{"label":"Productos","href":"/tienda"},{"label":"Repuestos","href":"/categoria/repuestos"},{"label":"SLIDER SHEET:ASS'Y Original PRO C9500 (1,200,000 págs al 5%)"}],"jsonLd":[{"@context":"https://schema.org","@type":"Product","name":"SLIDER SHEET:ASS'Y Original PRO C9500 (1,200,000 págs al 5%)","description":"SLIDER SHEET:ASS'Y Original PRO C9500 (1,200,000 págs al 5%)","sku":"M0EDL427","brand":{"@type":"Brand","name":"RICOH"},"offers":{"@type":"Offer","url":"https://www.haitech.pe/tienda/repuesto-m0edl427","availability":"https://schema.org/OutOfStock","seller":{"@type":"Organization","name":"HaiStore"},"itemCondition":"https://schema.org/NewCondition","priceValidUntil":"2026-10-14","priceCurrency":"USD","price":"329.90"},"mpn":"PRO C9500","model":"PRO C9500"},{"@context":"https://schema.org","@type":"BreadcrumbList","itemListElement":[{"@type":"ListItem","position":1,"name":"Inicio","item":"https://www.haitech.pe/"},{"@type":"ListItem","position":2,"name":"Productos","item":"https://www.haitech.pe/tienda"},{"@type":"ListItem","position":3,"name":"Repuestos","item":"https://www.haitech.pe/categoria/repuestos"},{"@type":"ListItem","position":4,"name":"SLIDER SHEET:ASS'Y Original PRO C9500 (1,200,000 págs al 5%)"}]}],"robots":"index,follow"}
