{"id":"repuesto-d2416006","slug":"repuesto-d2416006","pathname":"/tienda/producto/repuesto-d2416006","canonical":"https://www.haitech.pe/tienda/producto/repuesto-d2416006","title":"TRANSFER UNIT:INTERMEDIATE TRANSFER — Rend 240,00… | Haitech","description":"TRANSFER UNIT:INTERMEDIATE TRANSFER — MP C2004/ MP C2504 Desde S/ 2,354. Cotiza online con envío a todo el Perú.","image":"https://www.haitech.pe/categories/promonuevas-1.png","imageAlt":"TRANSFER UNIT:INTERMEDIATE TRANSFER — Rend 240,000 — MP C2004/ MP C2504","ogType":"product","ogProduct":{"priceAmount":"636.30","priceCurrency":"USD","priceAmountPen":"2354","availability":"out of stock","brand":"RICOH","retailerItemId":"D2416006"},"breadcrumbs":[{"label":"Inicio","href":"/"},{"label":"Productos","href":"/tienda"},{"label":"Repuestos","href":"/categoria/repuestos"},{"label":"TRANSFER UNIT:INTERMEDIATE TRANSFER — Rend 240,000 — MP C2004/ MP C2504"}],"jsonLd":[{"@context":"https://schema.org","@type":"Product","name":"TRANSFER UNIT:INTERMEDIATE TRANSFER — Rend 240,000 — MP C2004/ MP C2504","description":"TRANSFER UNIT:INTERMEDIATE TRANSFER — MP C2004/ MP C2504","sku":"D2416006","brand":{"@type":"Brand","name":"RICOH"},"offers":{"@type":"Offer","url":"https://www.haitech.pe/tienda/producto/repuesto-d2416006","availability":"https://schema.org/OutOfStock","seller":{"@type":"Organization","name":"Haitech"},"itemCondition":"https://schema.org/NewCondition","priceValidUntil":"2026-09-24","priceCurrency":"USD","price":"636.30"},"mpn":"MP C2004","model":"MP C2004"},{"@context":"https://schema.org","@type":"BreadcrumbList","itemListElement":[{"@type":"ListItem","position":1,"name":"Inicio","item":"https://www.haitech.pe/"},{"@type":"ListItem","position":2,"name":"Productos","item":"https://www.haitech.pe/tienda"},{"@type":"ListItem","position":3,"name":"Repuestos","item":"https://www.haitech.pe/categoria/repuestos"},{"@type":"ListItem","position":4,"name":"TRANSFER UNIT:INTERMEDIATE TRANSFER — Rend 240,000 — MP C2004/ MP C2504"}]}],"robots":"index,follow"}
