{"id":"repuesto-af033012","slug":"repuesto-af033012","pathname":"/tienda/producto/repuesto-af033012","canonical":"https://www.haitech.pe/tienda/producto/repuesto-af033012","title":"SEPARATION ROLLER/FRICTION PAD — IM-430F / P-502 … | Haitech","description":"SEPARATION ROLLER/FRICTION PAD (360,000 5%-A4) — IM-430F / P-502 Desde S/ 74. Cotiza online con envío a todo el Perú.","image":"https://www.haitech.pe/categories/promonuevas-1.png","imageAlt":"SEPARATION ROLLER/FRICTION PAD — IM-430F / P-502 (360,000 5%-A4)","ogType":"product","ogProduct":{"priceAmount":"19.90","priceCurrency":"USD","priceAmountPen":"74","availability":"out of stock","brand":"RICOH","retailerItemId":"AF033012"},"breadcrumbs":[{"label":"Inicio","href":"/"},{"label":"Productos","href":"/tienda"},{"label":"Repuestos, Repuestos Originales","href":"/categoria/repuestos"},{"label":"SEPARATION ROLLER/FRICTION PAD — IM-430F / P-502 (360,000 5%-A4)"}],"jsonLd":[{"@context":"https://schema.org","@type":"Product","name":"SEPARATION ROLLER/FRICTION PAD — IM-430F / P-502 (360,000 5%-A4)","description":"SEPARATION ROLLER/FRICTION PAD (360,000 5%-A4) — IM-430F / P-502","sku":"AF033012","brand":{"@type":"Brand","name":"RICOH"},"offers":{"@type":"Offer","url":"https://www.haitech.pe/tienda/producto/repuesto-af033012","availability":"https://schema.org/OutOfStock","seller":{"@type":"Organization","name":"Haitech","url":"https://www.haitech.pe","logo":"https://www.haitech.pe/Logo%20Haitech.png"},"itemCondition":"https://schema.org/NewCondition","priceValidUntil":"2026-09-24","priceCurrency":"USD","price":"19.90"}},{"@context":"https://schema.org","@type":"BreadcrumbList","itemListElement":[{"@type":"ListItem","position":1,"name":"Inicio","item":"https://www.haitech.pe/"},{"@type":"ListItem","position":2,"name":"Productos","item":"https://www.haitech.pe/tienda"},{"@type":"ListItem","position":3,"name":"Repuestos, Repuestos Originales","item":"https://www.haitech.pe/categoria/repuestos"},{"@type":"ListItem","position":4,"name":"SEPARATION ROLLER/FRICTION PAD — IM-430F / P-502 (360,000 5%-A4)"}]}],"robots":"index,follow"}
