{"id":"repuesto-d0e33001","slug":"repuesto-d0e33001","pathname":"/tienda/repuesto-d0e33001","canonical":"https://www.haitech.pe/tienda/repuesto-d0e33001","title":"[XREF TO D0E33065]DEVELOPMENT… | HaiStore","description":"[XREF TO D0E33065]DEVELOPMENT UNIT:C:IMC4510-6010 (unidad de revelado) Original IM C4510 IM C6010 (270,000 págs al 5%) Desde S/ 2,660. Cotiza online con envío…","image":"https://www.haitech.pe/categories/promonuevas-1.png","imageAlt":"[XREF TO D0E33065]DEVELOPMENT UNIT:C:IMC4510-6010 (unidad de revelado) Original IM C4510 IM C6010 (270,000 págs al 5%)","ogType":"product","ogProduct":{"priceAmount":"718.90","priceCurrency":"USD","priceAmountPen":"2660","availability":"out of stock","brand":"RICOH","retailerItemId":"D0E33001"},"breadcrumbs":[{"label":"Inicio","href":"/"},{"label":"Productos","href":"/tienda"},{"label":"Repuestos","href":"/categoria/repuestos"},{"label":"[XREF TO D0E33065]DEVELOPMENT UNIT:C:IMC4510-6010 (unidad de revelado) Original IM C4510 IM C6010 (270,000 págs al 5%)"}],"jsonLd":[{"@context":"https://schema.org","@type":"Product","name":"[XREF TO D0E33065]DEVELOPMENT UNIT:C:IMC4510-6010 (unidad de revelado) Original IM C4510 IM C6010 (270,000 págs al 5%)","description":"[XREF TO D0E33065]DEVELOPMENT UNIT:C:IMC4510-6010 (unidad de revelado) Original IM C4510 IM C6010 (270,000 págs al 5%)","sku":"D0E33001","brand":{"@type":"Brand","name":"RICOH"},"offers":{"@type":"Offer","url":"https://www.haitech.pe/tienda/repuesto-d0e33001","availability":"https://schema.org/OutOfStock","seller":{"@type":"Organization","name":"HaiStore"},"itemCondition":"https://schema.org/NewCondition","priceValidUntil":"2026-10-14","priceCurrency":"USD","price":"718.90"},"mpn":"IM C4510 IM C6010","model":"IM C4510 IM C6010"},{"@context":"https://schema.org","@type":"BreadcrumbList","itemListElement":[{"@type":"ListItem","position":1,"name":"Inicio","item":"https://www.haitech.pe/"},{"@type":"ListItem","position":2,"name":"Productos","item":"https://www.haitech.pe/tienda"},{"@type":"ListItem","position":3,"name":"Repuestos","item":"https://www.haitech.pe/categoria/repuestos"},{"@type":"ListItem","position":4,"name":"[XREF TO D0E33065]DEVELOPMENT UNIT:C:IMC4510-6010 (unidad de revelado) Original IM C4510 IM C6010 (270,000 págs al 5%)"}]}],"robots":"index,follow"}
