{"id":"ricoh-lp-3000011481-ps1","slug":"ricoh-lp-3000011481-ps1","pathname":"/tienda/producto/ricoh-lp-3000011481-ps1","canonical":"https://www.haitech.pe/tienda/producto/ricoh-lp-3000011481-ps1","title":"Fiery JobMaster - 3 Year Term License — PRO-8400… | HaiStore","description":"Fiery JobMaster - 3 Year Term License — PRO-8400s / PRO-8410s / PRO-8420s / PRO-8410 / PRO-8420 Desde S/ 39,009. Cotiza online con envío a todo el Perú.","image":"https://www.haitech.pe/categories/promonuevas-1.png","imageAlt":"Fiery JobMaster - 3 Year Term License — PRO-8400s / PRO-8410s / PRO-8420s / PRO-8410 / PRO-8420","ogType":"product","ogProduct":{"priceAmount":"10542.90","priceCurrency":"USD","priceAmountPen":"39009","availability":"out of stock","brand":"RICOH","retailerItemId":"3000011481PS1"},"breadcrumbs":[{"label":"Inicio","href":"/"},{"label":"Productos","href":"/tienda"},{"label":"Repuestos, Repuestos Originales","href":"/categoria/repuestos"},{"label":"Fiery JobMaster - 3 Year Term License — PRO-8400s / PRO-8410s / PRO-8420s / PRO-8410 / PRO-8420"}],"jsonLd":[{"@context":"https://schema.org","@type":"Product","name":"Fiery JobMaster - 3 Year Term License — PRO-8400s / PRO-8410s / PRO-8420s / PRO-8410 / PRO-8420","description":"Fiery JobMaster - 3 Year Term License — PRO-8400s / PRO-8410s / PRO-8420s / PRO-8410 / PRO-8420","sku":"3000011481PS1","brand":{"@type":"Brand","name":"RICOH"},"offers":{"@type":"Offer","url":"https://www.haitech.pe/tienda/producto/ricoh-lp-3000011481-ps1","availability":"https://schema.org/OutOfStock","seller":{"@type":"Organization","name":"HaiStore"},"itemCondition":"https://schema.org/NewCondition","priceValidUntil":"2026-10-01","priceCurrency":"USD","price":"10542.90"}},{"@context":"https://schema.org","@type":"BreadcrumbList","itemListElement":[{"@type":"ListItem","position":1,"name":"Inicio","item":"https://www.haitech.pe/"},{"@type":"ListItem","position":2,"name":"Productos","item":"https://www.haitech.pe/tienda"},{"@type":"ListItem","position":3,"name":"Repuestos, Repuestos Originales","item":"https://www.haitech.pe/categoria/repuestos"},{"@type":"ListItem","position":4,"name":"Fiery JobMaster - 3 Year Term License — PRO-8400s / PRO-8410s / PRO-8420s / PRO-8410 / PRO-8420"}]}],"robots":"index,follow"}
