{"id":"ricoh-lp-1665-02","slug":"ricoh-lp-1665-02","pathname":"/tienda/producto/ricoh-lp-1665-02","canonical":"https://www.haitech.pe/tienda/producto/ricoh-lp-1665-02","title":"Medium Cabinet — IM-550F / IM-600F / P-800 / P-801 | Haitech","description":"Medium Cabinet — IM-550F / IM-600F / P-800 / P-801 Desde S/ 754. Cotiza online con envío a todo el Perú.","image":"https://www.haitech.pe/categories/promonuevas-1.png","imageAlt":"Medium Cabinet — IM-550F / IM-600F / P-800 / P-801","ogType":"product","ogProduct":{"priceAmount":"203.90","priceCurrency":"USD","priceAmountPen":"754","availability":"out of stock","brand":"RICOH","retailerItemId":"166502"},"breadcrumbs":[{"label":"Inicio","href":"/"},{"label":"Productos","href":"/tienda"},{"label":"Repuestos, Repuestos Originales","href":"/categoria/repuestos"},{"label":"Medium Cabinet — IM-550F / IM-600F / P-800 / P-801"}],"jsonLd":[{"@context":"https://schema.org","@type":"Product","name":"Medium Cabinet — IM-550F / IM-600F / P-800 / P-801","description":"Medium Cabinet — IM-550F / IM-600F / P-800 / P-801","sku":"166502","brand":{"@type":"Brand","name":"RICOH"},"offers":{"@type":"Offer","url":"https://www.haitech.pe/tienda/producto/ricoh-lp-1665-02","availability":"https://schema.org/OutOfStock","seller":{"@type":"Organization","name":"Haitech"},"itemCondition":"https://schema.org/NewCondition","priceValidUntil":"2026-09-24","priceCurrency":"USD","price":"203.90"}},{"@context":"https://schema.org","@type":"BreadcrumbList","itemListElement":[{"@type":"ListItem","position":1,"name":"Inicio","item":"https://www.haitech.pe/"},{"@type":"ListItem","position":2,"name":"Productos","item":"https://www.haitech.pe/tienda"},{"@type":"ListItem","position":3,"name":"Repuestos, Repuestos Originales","item":"https://www.haitech.pe/categoria/repuestos"},{"@type":"ListItem","position":4,"name":"Medium Cabinet — IM-550F / IM-600F / P-800 / P-801"}]}],"robots":"index,follow"}
