{"id":"ricoh-lp-d0dk4051","slug":"ricoh-lp-d0dk4051","pathname":"/tienda/producto/ricoh-lp-d0dk4051","canonical":"https://www.haitech.pe/tienda/producto/ricoh-lp-d0dk4051","title":"FUSING UNIT — IM-2500 / IM-3000 / IM-4000 / IM-5… | HaiStore","description":"FUSING UNIT (240,000 5%-A4) — IM-2500 / IM-3000 / IM-4000 / IM-5000 / IM-6000 Desde S/ 2,061. Cotiza online con envío a todo el Perú.","image":"https://www.haitech.pe/categories/promonuevas-1.png","imageAlt":"FUSING UNIT — IM-2500 / IM-3000 / IM-4000 / IM-5000 / IM-6000 (240,000 5%-A4)","ogType":"product","ogProduct":{"priceAmount":"556.90","priceCurrency":"USD","priceAmountPen":"2061","availability":"out of stock","brand":"RICOH","retailerItemId":"D0DK4051"},"breadcrumbs":[{"label":"Inicio","href":"/"},{"label":"Productos","href":"/tienda"},{"label":"Repuestos, Repuestos Originales","href":"/categoria/repuestos"},{"label":"FUSING UNIT — IM-2500 / IM-3000 / IM-4000 / IM-5000 / IM-6000 (240,000 5%-A4)"}],"jsonLd":[{"@context":"https://schema.org","@type":"Product","name":"FUSING UNIT — IM-2500 / IM-3000 / IM-4000 / IM-5000 / IM-6000 (240,000 5%-A4)","description":"FUSING UNIT (240,000 5%-A4) — IM-2500 / IM-3000 / IM-4000 / IM-5000 / IM-6000","sku":"D0DK4051","brand":{"@type":"Brand","name":"RICOH"},"offers":{"@type":"Offer","url":"https://www.haitech.pe/tienda/producto/ricoh-lp-d0dk4051","availability":"https://schema.org/OutOfStock","seller":{"@type":"Organization","name":"HaiStore"},"itemCondition":"https://schema.org/NewCondition","priceValidUntil":"2026-10-01","priceCurrency":"USD","price":"556.90"}},{"@context":"https://schema.org","@type":"BreadcrumbList","itemListElement":[{"@type":"ListItem","position":1,"name":"Inicio","item":"https://www.haitech.pe/"},{"@type":"ListItem","position":2,"name":"Productos","item":"https://www.haitech.pe/tienda"},{"@type":"ListItem","position":3,"name":"Repuestos, Repuestos Originales","item":"https://www.haitech.pe/categoria/repuestos"},{"@type":"ListItem","position":4,"name":"FUSING UNIT — IM-2500 / IM-3000 / IM-4000 / IM-5000 / IM-6000 (240,000 5%-A4)"}]}],"robots":"index,follow"}
